{"league":{"admin_entry":333841,"closed":true,"draft_dt":"2025-08-15T11:00:00Z","draft_pick_time_limit":60,"draft_status":"pre","draft_tz_show":"Europe/London","id":65002,"ko_rounds":0,"make_code_public":false,"max_entries":12,"min_entries":12,"name":"A real sport","scoring":"h","start_event":1,"stop_event":38,"trades":"a","transaction_mode":"waivers","variety":"x","drafts":[{"id":68663,"draft_started":true,"draft_completed":"2025-08-15T12:07:34.531584Z","draft_dt":"2025-08-15T11:00:00Z","event":1,"league":65002,"order_method":"random"}],"is_renewed":false},"league_entries":[{"entry_id":333841,"entry_name":"Name TBD","id":333433,"joined_time":"2025-08-13T12:19:33.957683Z","player_first_name":"Simon","player_last_name":"Bidwell","short_name":"SB","waiver_pick":6},{"entry_id":334301,"entry_name":"Mitoma night's dream","id":333896,"joined_time":"2025-08-13T12:28:21.001129Z","player_first_name":"Ed","player_last_name":"Brett","short_name":"EB","waiver_pick":3},{"entry_id":335088,"entry_name":"Atomic Gittens","id":334690,"joined_time":"2025-08-13T12:42:26.228626Z","player_first_name":"Alex","player_last_name":"Harrison","short_name":"AH","waiver_pick":8},{"entry_id":335728,"entry_name":"Will Still Standing","id":335338,"joined_time":"2025-08-13T12:56:35.902075Z","player_first_name":"Oliver","player_last_name":"Craig","short_name":"OC","waiver_pick":4},{"entry_id":335912,"entry_name":"European Champions","id":335523,"joined_time":"2025-08-13T13:00:27.862280Z","player_first_name":"Luke","player_last_name":"Trevett","short_name":"LT","waiver_pick":10},{"entry_id":341006,"entry_name":"DontLookBackElanga","id":340643,"joined_time":"2025-08-13T14:46:47.515084Z","player_first_name":"Jonathan","player_last_name":"Purvis","short_name":"JP","waiver_pick":7},{"entry_id":344919,"entry_name":"Hawk Tchouaméni","id":344571,"joined_time":"2025-08-13T16:01:43.969190Z","player_first_name":"Sam","player_last_name":"Senior","short_name":"SS","waiver_pick":2},{"entry_id":362708,"entry_name":"Wirtz decision ever","id":362777,"joined_time":"2025-08-13T21:08:42.194803Z","player_first_name":"Anjit","player_last_name":"Aulakh","short_name":"AA","waiver_pick":9},{"entry_id":375295,"entry_name":"Al Sesko Dining","id":375720,"joined_time":"2025-08-14T05:27:01.166987Z","player_first_name":"Alexander","player_last_name":"Greenhalgh","short_name":"AG","waiver_pick":1},{"entry_id":391545,"entry_name":"Šeško Meal Deal","id":392127,"joined_time":"2025-08-14T13:32:29.902399Z","player_first_name":"Ben","player_last_name":"Malpass","short_name":"BM","waiver_pick":11},{"entry_id":399667,"entry_name":"Go with the Flo","id":400317,"joined_time":"2025-08-14T16:10:49.106800Z","player_first_name":"Sebastian","player_last_name":"Waters","short_name":"SW","waiver_pick":12},{"entry_id":421637,"entry_name":"Kinder Mbuemo","id":422898,"joined_time":"2025-08-14T21:32:35.413491Z","player_first_name":"Aaron","player_last_name":"Veale","short_name":"AV","waiver_pick":5}],"matches":[{"event":1,"finished":true,"league_entry_1":362777,"league_entry_1_points":42,"league_entry_2":333433,"league_entry_2_points":33,"started":true,"winning_league_entry":null,"winning_method":null},{"event":1,"finished":true,"league_entry_1":375720,"league_entry_1_points":24,"league_entry_2":344571,"league_entry_2_points":39,"started":true,"winning_league_entry":null,"winning_method":null},{"event":1,"finished":true,"league_entry_1":392127,"league_entry_1_points":48,"league_entry_2":340643,"league_entry_2_points":33,"started":true,"winning_league_entry":null,"winning_method":null},{"event":1,"finished":true,"league_entry_1":400317,"league_entry_1_points":60,"league_entry_2":335523,"league_entry_2_points":36,"started":true,"winning_league_entry":null,"winning_method":null},{"event":1,"finished":true,"league_entry_1":422898,"league_entry_1_points":32,"league_entry_2":335338,"league_entry_2_points":70,"started":true,"winning_league_entry":null,"winning_method":null},{"event":1,"finished":true,"league_entry_1":333896,"league_entry_1_points":36,"league_entry_2":334690,"league_entry_2_points":52,"started":true,"winning_league_entry":null,"winning_method":null},{"event":2,"finished":true,"league_entry_1":333433,"league_entry_1_points":37,"league_entry_2":333896,"league_entry_2_points":15,"started":true,"winning_league_entry":null,"winning_method":null},{"event":2,"finished":true,"league_entry_1":334690,"league_entry_1_points":49,"league_entry_2":422898,"league_entry_2_points":64,"started":true,"winning_league_entry":null,"winning_method":null},{"event":2,"finished":true,"league_entry_1":335338,"league_entry_1_points":42,"league_entry_2":400317,"league_entry_2_points":44,"started":true,"winning_league_entry":null,"winning_method":null},{"event":2,"finished":true,"league_entry_1":335523,"league_entry_1_points":30,"league_entry_2":392127,"league_entry_2_points":57,"started":true,"winning_league_entry":null,"winning_method":null},{"event":2,"finished":true,"league_entry_1":340643,"league_entry_1_points":40,"league_entry_2":375720,"league_entry_2_points":30,"started":true,"winning_league_entry":null,"winning_method":null},{"event":2,"finished":true,"league_entry_1":344571,"league_entry_1_points":40,"league_entry_2":362777,"league_entry_2_points":31,"started":true,"winning_league_entry":null,"winning_method":null},{"event":3,"finished":true,"league_entry_1":375720,"league_entry_1_points":36,"league_entry_2":333433,"league_entry_2_points":27,"started":true,"winning_league_entry":null,"winning_method":null},{"event":3,"finished":true,"league_entry_1":392127,"league_entry_1_points":38,"league_entry_2":362777,"league_entry_2_points":56,"started":true,"winning_league_entry":null,"winning_method":null},{"event":3,"finished":true,"league_entry_1":400317,"league_entry_1_points":45,"league_entry_2":344571,"league_entry_2_points":62,"started":true,"winning_league_entry":null,"winning_method":null},{"event":3,"finished":true,"league_entry_1":422898,"league_entry_1_points":34,"league_entry_2":340643,"league_entry_2_points":42,"started":true,"winning_league_entry":null,"winning_method":null},{"event":3,"finished":true,"league_entry_1":333896,"league_entry_1_points":25,"league_entry_2":335523,"league_entry_2_points":39,"started":true,"winning_league_entry":null,"winning_method":null},{"event":3,"finished":true,"league_entry_1":334690,"league_entry_1_points":43,"league_entry_2":335338,"league_entry_2_points":35,"started":true,"winning_league_entry":null,"winning_method":null},{"event":4,"finished":true,"league_entry_1":333433,"league_entry_1_points":31,"league_entry_2":334690,"league_entry_2_points":34,"started":true,"winning_league_entry":null,"winning_method":null},{"event":4,"finished":true,"league_entry_1":335338,"league_entry_1_points":32,"league_entry_2":333896,"league_entry_2_points":44,"started":true,"winning_league_entry":null,"winning_method":null},{"event":4,"finished":true,"league_entry_1":335523,"league_entry_1_points":49,"league_entry_2":422898,"league_entry_2_points":49,"started":true,"winning_league_entry":null,"winning_method":null},{"event":4,"finished":true,"league_entry_1":340643,"league_entry_1_points":56,"league_entry_2":400317,"league_entry_2_points":62,"started":true,"winning_league_entry":null,"winning_method":null},{"event":4,"finished":true,"league_entry_1":344571,"league_entry_1_points":45,"league_entry_2":392127,"league_entry_2_points":49,"started":true,"winning_league_entry":null,"winning_method":null},{"event":4,"finished":true,"league_entry_1":362777,"league_entry_1_points":33,"league_entry_2":375720,"league_entry_2_points":39,"started":true,"winning_league_entry":null,"winning_method":null},{"event":5,"finished":true,"league_entry_1":392127,"league_entry_1_points":29,"league_entry_2":333433,"league_entry_2_points":24,"started":true,"winning_league_entry":null,"winning_method":null},{"event":5,"finished":true,"league_entry_1":400317,"league_entry_1_points":45,"league_entry_2":375720,"league_entry_2_points":36,"started":true,"winning_league_entry":null,"winning_method":null},{"event":5,"finished":true,"league_entry_1":422898,"league_entry_1_points":28,"league_entry_2":362777,"league_entry_2_points":53,"started":true,"winning_league_entry":null,"winning_method":null},{"event":5,"finished":true,"league_entry_1":333896,"league_entry_1_points":42,"league_entry_2":344571,"league_entry_2_points":42,"started":true,"winning_league_entry":null,"winning_method":null},{"event":5,"finished":true,"league_entry_1":334690,"league_entry_1_points":31,"league_entry_2":340643,"league_entry_2_points":47,"started":true,"winning_league_entry":null,"winning_method":null},{"event":5,"finished":true,"league_entry_1":335338,"league_entry_1_points":26,"league_entry_2":335523,"league_entry_2_points":26,"started":true,"winning_league_entry":null,"winning_method":null},{"event":6,"finished":true,"league_entry_1":333433,"league_entry_1_points":29,"league_entry_2":335338,"league_entry_2_points":34,"started":true,"winning_league_entry":null,"winning_method":null},{"event":6,"finished":true,"league_entry_1":335523,"league_entry_1_points":42,"league_entry_2":334690,"league_entry_2_points":19,"started":true,"winning_league_entry":null,"winning_method":null},{"event":6,"finished":true,"league_entry_1":340643,"league_entry_1_points":25,"league_entry_2":333896,"league_entry_2_points":38,"started":true,"winning_league_entry":null,"winning_method":null},{"event":6,"finished":true,"league_entry_1":344571,"league_entry_1_points":27,"league_entry_2":422898,"league_entry_2_points":20,"started":true,"winning_league_entry":null,"winning_method":null},{"event":6,"finished":true,"league_entry_1":362777,"league_entry_1_points":16,"league_entry_2":400317,"league_entry_2_points":46,"started":true,"winning_league_entry":null,"winning_method":null},{"event":6,"finished":true,"league_entry_1":375720,"league_entry_1_points":45,"league_entry_2":392127,"league_entry_2_points":37,"started":true,"winning_league_entry":null,"winning_method":null},{"event":7,"finished":true,"league_entry_1":400317,"league_entry_1_points":61,"league_entry_2":333433,"league_entry_2_points":29,"started":true,"winning_league_entry":null,"winning_method":null},{"event":7,"finished":true,"league_entry_1":422898,"league_entry_1_points":40,"league_entry_2":392127,"league_entry_2_points":53,"started":true,"winning_league_entry":null,"winning_method":null},{"event":7,"finished":true,"league_entry_1":333896,"league_entry_1_points":50,"league_entry_2":375720,"league_entry_2_points":30,"started":true,"winning_league_entry":null,"winning_method":null},{"event":7,"finished":true,"league_entry_1":334690,"league_entry_1_points":40,"league_entry_2":362777,"league_entry_2_points":54,"started":true,"winning_league_entry":null,"winning_method":null},{"event":7,"finished":true,"league_entry_1":335338,"league_entry_1_points":48,"league_entry_2":344571,"league_entry_2_points":9,"started":true,"winning_league_entry":null,"winning_method":null},{"event":7,"finished":true,"league_entry_1":335523,"league_entry_1_points":48,"league_entry_2":340643,"league_entry_2_points":24,"started":true,"winning_league_entry":null,"winning_method":null},{"event":8,"finished":true,"league_entry_1":333433,"league_entry_1_points":31,"league_entry_2":335523,"league_entry_2_points":38,"started":true,"winning_league_entry":null,"winning_method":null},{"event":8,"finished":true,"league_entry_1":340643,"league_entry_1_points":29,"league_entry_2":335338,"league_entry_2_points":27,"started":true,"winning_league_entry":null,"winning_method":null},{"event":8,"finished":true,"league_entry_1":344571,"league_entry_1_points":25,"league_entry_2":334690,"league_entry_2_points":29,"started":true,"winning_league_entry":null,"winning_method":null},{"event":8,"finished":true,"league_entry_1":362777,"league_entry_1_points":60,"league_entry_2":333896,"league_entry_2_points":44,"started":true,"winning_league_entry":null,"winning_method":null},{"event":8,"finished":true,"league_entry_1":375720,"league_entry_1_points":44,"league_entry_2":422898,"league_entry_2_points":45,"started":true,"winning_league_entry":null,"winning_method":null},{"event":8,"finished":true,"league_entry_1":392127,"league_entry_1_points":50,"league_entry_2":400317,"league_entry_2_points":49,"started":true,"winning_league_entry":null,"winning_method":null},{"event":9,"finished":true,"league_entry_1":422898,"league_entry_1_points":23,"league_entry_2":333433,"league_entry_2_points":31,"started":true,"winning_league_entry":null,"winning_method":null},{"event":9,"finished":true,"league_entry_1":333896,"league_entry_1_points":52,"league_entry_2":400317,"league_entry_2_points":56,"started":true,"winning_league_entry":null,"winning_method":null},{"event":9,"finished":true,"league_entry_1":334690,"league_entry_1_points":38,"league_entry_2":392127,"league_entry_2_points":26,"started":true,"winning_league_entry":null,"winning_method":null},{"event":9,"finished":true,"league_entry_1":335338,"league_entry_1_points":33,"league_entry_2":375720,"league_entry_2_points":44,"started":true,"winning_league_entry":null,"winning_method":null},{"event":9,"finished":true,"league_entry_1":335523,"league_entry_1_points":48,"league_entry_2":362777,"league_entry_2_points":35,"started":true,"winning_league_entry":null,"winning_method":null},{"event":9,"finished":true,"league_entry_1":340643,"league_entry_1_points":57,"league_entry_2":344571,"league_entry_2_points":24,"started":true,"winning_league_entry":null,"winning_method":null},{"event":10,"finished":true,"league_entry_1":333433,"league_entry_1_points":28,"league_entry_2":340643,"league_entry_2_points":33,"started":true,"winning_league_entry":null,"winning_method":null},{"event":10,"finished":true,"league_entry_1":344571,"league_entry_1_points":27,"league_entry_2":335523,"league_entry_2_points":41,"started":true,"winning_league_entry":null,"winning_method":null},{"event":10,"finished":true,"league_entry_1":362777,"league_entry_1_points":44,"league_entry_2":335338,"league_entry_2_points":48,"started":true,"winning_league_entry":null,"winning_method":null},{"event":10,"finished":true,"league_entry_1":375720,"league_entry_1_points":17,"league_entry_2":334690,"league_entry_2_points":30,"started":true,"winning_league_entry":null,"winning_method":null},{"event":10,"finished":true,"league_entry_1":392127,"league_entry_1_points":65,"league_entry_2":333896,"league_entry_2_points":39,"started":true,"winning_league_entry":null,"winning_method":null},{"event":10,"finished":true,"league_entry_1":400317,"league_entry_1_points":48,"league_entry_2":422898,"league_entry_2_points":43,"started":true,"winning_league_entry":null,"winning_method":null},{"event":11,"finished":true,"league_entry_1":344571,"league_entry_1_points":24,"league_entry_2":333433,"league_entry_2_points":41,"started":true,"winning_league_entry":null,"winning_method":null},{"event":11,"finished":true,"league_entry_1":362777,"league_entry_1_points":41,"league_entry_2":340643,"league_entry_2_points":43,"started":true,"winning_league_entry":null,"winning_method":null},{"event":11,"finished":true,"league_entry_1":375720,"league_entry_1_points":76,"league_entry_2":335523,"league_entry_2_points":45,"started":true,"winning_league_entry":null,"winning_method":null},{"event":11,"finished":true,"league_entry_1":392127,"league_entry_1_points":37,"league_entry_2":335338,"league_entry_2_points":26,"started":true,"winning_league_entry":null,"winning_method":null},{"event":11,"finished":true,"league_entry_1":400317,"league_entry_1_points":49,"league_entry_2":334690,"league_entry_2_points":43,"started":true,"winning_league_entry":null,"winning_method":null},{"event":11,"finished":true,"league_entry_1":422898,"league_entry_1_points":39,"league_entry_2":333896,"league_entry_2_points":45,"started":true,"winning_league_entry":null,"winning_method":null},{"event":12,"finished":true,"league_entry_1":362777,"league_entry_1_points":36,"league_entry_2":333433,"league_entry_2_points":38,"started":true,"winning_league_entry":null,"winning_method":null},{"event":12,"finished":true,"league_entry_1":375720,"league_entry_1_points":50,"league_entry_2":344571,"league_entry_2_points":31,"started":true,"winning_league_entry":null,"winning_method":null},{"event":12,"finished":true,"league_entry_1":392127,"league_entry_1_points":50,"league_entry_2":340643,"league_entry_2_points":34,"started":true,"winning_league_entry":null,"winning_method":null},{"event":12,"finished":true,"league_entry_1":400317,"league_entry_1_points":51,"league_entry_2":335523,"league_entry_2_points":29,"started":true,"winning_league_entry":null,"winning_method":null},{"event":12,"finished":true,"league_entry_1":422898,"league_entry_1_points":30,"league_entry_2":335338,"league_entry_2_points":28,"started":true,"winning_league_entry":null,"winning_method":null},{"event":12,"finished":true,"league_entry_1":333896,"league_entry_1_points":59,"league_entry_2":334690,"league_entry_2_points":44,"started":true,"winning_league_entry":null,"winning_method":null},{"event":13,"finished":true,"league_entry_1":333433,"league_entry_1_points":39,"league_entry_2":333896,"league_entry_2_points":38,"started":true,"winning_league_entry":null,"winning_method":null},{"event":13,"finished":true,"league_entry_1":334690,"league_entry_1_points":30,"league_entry_2":422898,"league_entry_2_points":41,"started":true,"winning_league_entry":null,"winning_method":null},{"event":13,"finished":true,"league_entry_1":335338,"league_entry_1_points":26,"league_entry_2":400317,"league_entry_2_points":24,"started":true,"winning_league_entry":null,"winning_method":null},{"event":13,"finished":true,"league_entry_1":335523,"league_entry_1_points":24,"league_entry_2":392127,"league_entry_2_points":49,"started":true,"winning_league_entry":null,"winning_method":null},{"event":13,"finished":true,"league_entry_1":340643,"league_entry_1_points":52,"league_entry_2":375720,"league_entry_2_points":19,"started":true,"winning_league_entry":null,"winning_method":null},{"event":13,"finished":true,"league_entry_1":344571,"league_entry_1_points":26,"league_entry_2":362777,"league_entry_2_points":42,"started":true,"winning_league_entry":null,"winning_method":null},{"event":14,"finished":true,"league_entry_1":375720,"league_entry_1_points":40,"league_entry_2":333433,"league_entry_2_points":48,"started":true,"winning_league_entry":null,"winning_method":null},{"event":14,"finished":true,"league_entry_1":392127,"league_entry_1_points":41,"league_entry_2":362777,"league_entry_2_points":55,"started":true,"winning_league_entry":null,"winning_method":null},{"event":14,"finished":true,"league_entry_1":400317,"league_entry_1_points":43,"league_entry_2":344571,"league_entry_2_points":31,"started":true,"winning_league_entry":null,"winning_method":null},{"event":14,"finished":true,"league_entry_1":422898,"league_entry_1_points":52,"league_entry_2":340643,"league_entry_2_points":22,"started":true,"winning_league_entry":null,"winning_method":null},{"event":14,"finished":true,"league_entry_1":333896,"league_entry_1_points":31,"league_entry_2":335523,"league_entry_2_points":43,"started":true,"winning_league_entry":null,"winning_method":null},{"event":14,"finished":true,"league_entry_1":334690,"league_entry_1_points":39,"league_entry_2":335338,"league_entry_2_points":57,"started":true,"winning_league_entry":null,"winning_method":null},{"event":15,"finished":true,"league_entry_1":333433,"league_entry_1_points":49,"league_entry_2":334690,"league_entry_2_points":71,"started":true,"winning_league_entry":null,"winning_method":null},{"event":15,"finished":true,"league_entry_1":335338,"league_entry_1_points":37,"league_entry_2":333896,"league_entry_2_points":44,"started":true,"winning_league_entry":null,"winning_method":null},{"event":15,"finished":true,"league_entry_1":335523,"league_entry_1_points":44,"league_entry_2":422898,"league_entry_2_points":40,"started":true,"winning_league_entry":null,"winning_method":null},{"event":15,"finished":true,"league_entry_1":340643,"league_entry_1_points":33,"league_entry_2":400317,"league_entry_2_points":49,"started":true,"winning_league_entry":null,"winning_method":null},{"event":15,"finished":true,"league_entry_1":344571,"league_entry_1_points":44,"league_entry_2":392127,"league_entry_2_points":29,"started":true,"winning_league_entry":null,"winning_method":null},{"event":15,"finished":true,"league_entry_1":362777,"league_entry_1_points":64,"league_entry_2":375720,"league_entry_2_points":54,"started":true,"winning_league_entry":null,"winning_method":null},{"event":16,"finished":true,"league_entry_1":392127,"league_entry_1_points":63,"league_entry_2":333433,"league_entry_2_points":28,"started":true,"winning_league_entry":null,"winning_method":null},{"event":16,"finished":true,"league_entry_1":400317,"league_entry_1_points":64,"league_entry_2":375720,"league_entry_2_points":22,"started":true,"winning_league_entry":null,"winning_method":null},{"event":16,"finished":true,"league_entry_1":422898,"league_entry_1_points":46,"league_entry_2":362777,"league_entry_2_points":45,"started":true,"winning_league_entry":null,"winning_method":null},{"event":16,"finished":true,"league_entry_1":333896,"league_entry_1_points":51,"league_entry_2":344571,"league_entry_2_points":29,"started":true,"winning_league_entry":null,"winning_method":null},{"event":16,"finished":true,"league_entry_1":334690,"league_entry_1_points":36,"league_entry_2":340643,"league_entry_2_points":18,"started":true,"winning_league_entry":null,"winning_method":null},{"event":16,"finished":true,"league_entry_1":335338,"league_entry_1_points":36,"league_entry_2":335523,"league_entry_2_points":34,"started":true,"winning_league_entry":null,"winning_method":null},{"event":17,"finished":true,"league_entry_1":333433,"league_entry_1_points":43,"league_entry_2":335338,"league_entry_2_points":38,"started":true,"winning_league_entry":null,"winning_method":null},{"event":17,"finished":true,"league_entry_1":335523,"league_entry_1_points":26,"league_entry_2":334690,"league_entry_2_points":38,"started":true,"winning_league_entry":null,"winning_method":null},{"event":17,"finished":true,"league_entry_1":340643,"league_entry_1_points":29,"league_entry_2":333896,"league_entry_2_points":39,"started":true,"winning_league_entry":null,"winning_method":null},{"event":17,"finished":true,"league_entry_1":344571,"league_entry_1_points":25,"league_entry_2":422898,"league_entry_2_points":44,"started":true,"winning_league_entry":null,"winning_method":null},{"event":17,"finished":true,"league_entry_1":362777,"league_entry_1_points":44,"league_entry_2":400317,"league_entry_2_points":41,"started":true,"winning_league_entry":null,"winning_method":null},{"event":17,"finished":true,"league_entry_1":375720,"league_entry_1_points":33,"league_entry_2":392127,"league_entry_2_points":66,"started":true,"winning_league_entry":null,"winning_method":null},{"event":18,"finished":true,"league_entry_1":400317,"league_entry_1_points":36,"league_entry_2":333433,"league_entry_2_points":44,"started":true,"winning_league_entry":null,"winning_method":null},{"event":18,"finished":true,"league_entry_1":422898,"league_entry_1_points":38,"league_entry_2":392127,"league_entry_2_points":33,"started":true,"winning_league_entry":null,"winning_method":null},{"event":18,"finished":true,"league_entry_1":333896,"league_entry_1_points":40,"league_entry_2":375720,"league_entry_2_points":28,"started":true,"winning_league_entry":null,"winning_method":null},{"event":18,"finished":true,"league_entry_1":334690,"league_entry_1_points":35,"league_entry_2":362777,"league_entry_2_points":50,"started":true,"winning_league_entry":null,"winning_method":null},{"event":18,"finished":true,"league_entry_1":335338,"league_entry_1_points":45,"league_entry_2":344571,"league_entry_2_points":26,"started":true,"winning_league_entry":null,"winning_method":null},{"event":18,"finished":true,"league_entry_1":335523,"league_entry_1_points":49,"league_entry_2":340643,"league_entry_2_points":33,"started":true,"winning_league_entry":null,"winning_method":null},{"event":19,"finished":true,"league_entry_1":333433,"league_entry_1_points":35,"league_entry_2":335523,"league_entry_2_points":54,"started":true,"winning_league_entry":null,"winning_method":null},{"event":19,"finished":true,"league_entry_1":340643,"league_entry_1_points":34,"league_entry_2":335338,"league_entry_2_points":31,"started":true,"winning_league_entry":null,"winning_method":null},{"event":19,"finished":true,"league_entry_1":344571,"league_entry_1_points":62,"league_entry_2":334690,"league_entry_2_points":44,"started":true,"winning_league_entry":null,"winning_method":null},{"event":19,"finished":true,"league_entry_1":362777,"league_entry_1_points":45,"league_entry_2":333896,"league_entry_2_points":30,"started":true,"winning_league_entry":null,"winning_method":null},{"event":19,"finished":true,"league_entry_1":375720,"league_entry_1_points":54,"league_entry_2":422898,"league_entry_2_points":22,"started":true,"winning_league_entry":null,"winning_method":null},{"event":19,"finished":true,"league_entry_1":392127,"league_entry_1_points":39,"league_entry_2":400317,"league_entry_2_points":40,"started":true,"winning_league_entry":null,"winning_method":null},{"event":20,"finished":true,"league_entry_1":422898,"league_entry_1_points":33,"league_entry_2":333433,"league_entry_2_points":35,"started":true,"winning_league_entry":null,"winning_method":null},{"event":20,"finished":true,"league_entry_1":333896,"league_entry_1_points":18,"league_entry_2":400317,"league_entry_2_points":53,"started":true,"winning_league_entry":null,"winning_method":null},{"event":20,"finished":true,"league_entry_1":334690,"league_entry_1_points":49,"league_entry_2":392127,"league_entry_2_points":59,"started":true,"winning_league_entry":null,"winning_method":null},{"event":20,"finished":true,"league_entry_1":335338,"league_entry_1_points":59,"league_entry_2":375720,"league_entry_2_points":25,"started":true,"winning_league_entry":null,"winning_method":null},{"event":20,"finished":true,"league_entry_1":335523,"league_entry_1_points":30,"league_entry_2":362777,"league_entry_2_points":19,"started":true,"winning_league_entry":null,"winning_method":null},{"event":20,"finished":true,"league_entry_1":340643,"league_entry_1_points":37,"league_entry_2":344571,"league_entry_2_points":35,"started":true,"winning_league_entry":null,"winning_method":null},{"event":21,"finished":true,"league_entry_1":333433,"league_entry_1_points":30,"league_entry_2":340643,"league_entry_2_points":39,"started":true,"winning_league_entry":null,"winning_method":null},{"event":21,"finished":true,"league_entry_1":344571,"league_entry_1_points":34,"league_entry_2":335523,"league_entry_2_points":52,"started":true,"winning_league_entry":null,"winning_method":null},{"event":21,"finished":true,"league_entry_1":362777,"league_entry_1_points":41,"league_entry_2":335338,"league_entry_2_points":21,"started":true,"winning_league_entry":null,"winning_method":null},{"event":21,"finished":true,"league_entry_1":375720,"league_entry_1_points":36,"league_entry_2":334690,"league_entry_2_points":42,"started":true,"winning_league_entry":null,"winning_method":null},{"event":21,"finished":true,"league_entry_1":392127,"league_entry_1_points":42,"league_entry_2":333896,"league_entry_2_points":33,"started":true,"winning_league_entry":null,"winning_method":null},{"event":21,"finished":true,"league_entry_1":400317,"league_entry_1_points":56,"league_entry_2":422898,"league_entry_2_points":41,"started":true,"winning_league_entry":null,"winning_method":null},{"event":22,"finished":true,"league_entry_1":344571,"league_entry_1_points":41,"league_entry_2":333433,"league_entry_2_points":25,"started":true,"winning_league_entry":null,"winning_method":null},{"event":22,"finished":true,"league_entry_1":362777,"league_entry_1_points":54,"league_entry_2":340643,"league_entry_2_points":32,"started":true,"winning_league_entry":null,"winning_method":null},{"event":22,"finished":true,"league_entry_1":375720,"league_entry_1_points":52,"league_entry_2":335523,"league_entry_2_points":35,"started":true,"winning_league_entry":null,"winning_method":null},{"event":22,"finished":true,"league_entry_1":392127,"league_entry_1_points":39,"league_entry_2":335338,"league_entry_2_points":49,"started":true,"winning_league_entry":null,"winning_method":null},{"event":22,"finished":true,"league_entry_1":400317,"league_entry_1_points":30,"league_entry_2":334690,"league_entry_2_points":38,"started":true,"winning_league_entry":null,"winning_method":null},{"event":22,"finished":true,"league_entry_1":422898,"league_entry_1_points":44,"league_entry_2":333896,"league_entry_2_points":32,"started":true,"winning_league_entry":null,"winning_method":null},{"event":23,"finished":true,"league_entry_1":362777,"league_entry_1_points":44,"league_entry_2":333433,"league_entry_2_points":51,"started":true,"winning_league_entry":null,"winning_method":null},{"event":23,"finished":true,"league_entry_1":375720,"league_entry_1_points":30,"league_entry_2":344571,"league_entry_2_points":48,"started":true,"winning_league_entry":null,"winning_method":null},{"event":23,"finished":true,"league_entry_1":392127,"league_entry_1_points":50,"league_entry_2":340643,"league_entry_2_points":27,"started":true,"winning_league_entry":null,"winning_method":null},{"event":23,"finished":true,"league_entry_1":400317,"league_entry_1_points":53,"league_entry_2":335523,"league_entry_2_points":19,"started":true,"winning_league_entry":null,"winning_method":null},{"event":23,"finished":true,"league_entry_1":422898,"league_entry_1_points":50,"league_entry_2":335338,"league_entry_2_points":36,"started":true,"winning_league_entry":null,"winning_method":null},{"event":23,"finished":true,"league_entry_1":333896,"league_entry_1_points":31,"league_entry_2":334690,"league_entry_2_points":42,"started":true,"winning_league_entry":null,"winning_method":null},{"event":24,"finished":true,"league_entry_1":333433,"league_entry_1_points":46,"league_entry_2":333896,"league_entry_2_points":21,"started":true,"winning_league_entry":null,"winning_method":null},{"event":24,"finished":true,"league_entry_1":334690,"league_entry_1_points":42,"league_entry_2":422898,"league_entry_2_points":44,"started":true,"winning_league_entry":null,"winning_method":null},{"event":24,"finished":true,"league_entry_1":335338,"league_entry_1_points":49,"league_entry_2":400317,"league_entry_2_points":52,"started":true,"winning_league_entry":null,"winning_method":null},{"event":24,"finished":true,"league_entry_1":335523,"league_entry_1_points":47,"league_entry_2":392127,"league_entry_2_points":41,"started":true,"winning_league_entry":null,"winning_method":null},{"event":24,"finished":true,"league_entry_1":340643,"league_entry_1_points":60,"league_entry_2":375720,"league_entry_2_points":35,"started":true,"winning_league_entry":null,"winning_method":null},{"event":24,"finished":true,"league_entry_1":344571,"league_entry_1_points":42,"league_entry_2":362777,"league_entry_2_points":33,"started":true,"winning_league_entry":null,"winning_method":null},{"event":25,"finished":true,"league_entry_1":375720,"league_entry_1_points":38,"league_entry_2":333433,"league_entry_2_points":49,"started":true,"winning_league_entry":null,"winning_method":null},{"event":25,"finished":true,"league_entry_1":392127,"league_entry_1_points":51,"league_entry_2":362777,"league_entry_2_points":64,"started":true,"winning_league_entry":null,"winning_method":null},{"event":25,"finished":true,"league_entry_1":400317,"league_entry_1_points":27,"league_entry_2":344571,"league_entry_2_points":58,"started":true,"winning_league_entry":null,"winning_method":null},{"event":25,"finished":true,"league_entry_1":422898,"league_entry_1_points":36,"league_entry_2":340643,"league_entry_2_points":43,"started":true,"winning_league_entry":null,"winning_method":null},{"event":25,"finished":true,"league_entry_1":333896,"league_entry_1_points":48,"league_entry_2":335523,"league_entry_2_points":28,"started":true,"winning_league_entry":null,"winning_method":null},{"event":25,"finished":true,"league_entry_1":334690,"league_entry_1_points":36,"league_entry_2":335338,"league_entry_2_points":34,"started":true,"winning_league_entry":null,"winning_method":null},{"event":26,"finished":true,"league_entry_1":333433,"league_entry_1_points":36,"league_entry_2":334690,"league_entry_2_points":22,"started":true,"winning_league_entry":null,"winning_method":null},{"event":26,"finished":true,"league_entry_1":335338,"league_entry_1_points":40,"league_entry_2":333896,"league_entry_2_points":34,"started":true,"winning_league_entry":null,"winning_method":null},{"event":26,"finished":true,"league_entry_1":335523,"league_entry_1_points":69,"league_entry_2":422898,"league_entry_2_points":66,"started":true,"winning_league_entry":null,"winning_method":null},{"event":26,"finished":true,"league_entry_1":340643,"league_entry_1_points":41,"league_entry_2":400317,"league_entry_2_points":48,"started":true,"winning_league_entry":null,"winning_method":null},{"event":26,"finished":true,"league_entry_1":344571,"league_entry_1_points":36,"league_entry_2":392127,"league_entry_2_points":39,"started":true,"winning_league_entry":null,"winning_method":null},{"event":26,"finished":true,"league_entry_1":362777,"league_entry_1_points":21,"league_entry_2":375720,"league_entry_2_points":22,"started":true,"winning_league_entry":null,"winning_method":null},{"event":27,"finished":false,"league_entry_1":392127,"league_entry_1_points":9,"league_entry_2":333433,"league_entry_2_points":14,"started":true,"winning_league_entry":null,"winning_method":null},{"event":27,"finished":false,"league_entry_1":400317,"league_entry_1_points":20,"league_entry_2":375720,"league_entry_2_points":12,"started":true,"winning_league_entry":null,"winning_method":null},{"event":27,"finished":false,"league_entry_1":422898,"league_entry_1_points":33,"league_entry_2":362777,"league_entry_2_points":11,"started":true,"winning_league_entry":null,"winning_method":null},{"event":27,"finished":false,"league_entry_1":333896,"league_entry_1_points":40,"league_entry_2":344571,"league_entry_2_points":10,"started":true,"winning_league_entry":null,"winning_method":null},{"event":27,"finished":false,"league_entry_1":334690,"league_entry_1_points":13,"league_entry_2":340643,"league_entry_2_points":15,"started":true,"winning_league_entry":null,"winning_method":null},{"event":27,"finished":false,"league_entry_1":335338,"league_entry_1_points":14,"league_entry_2":335523,"league_entry_2_points":6,"started":true,"winning_league_entry":null,"winning_method":null},{"event":28,"finished":false,"league_entry_1":333433,"league_entry_1_points":0,"league_entry_2":335338,"league_entry_2_points":0,"started":false,"winning_league_entry":null,"winning_method":null},{"event":28,"finished":false,"league_entry_1":335523,"league_entry_1_points":0,"league_entry_2":334690,"league_entry_2_points":0,"started":false,"winning_league_entry":null,"winning_method":null},{"event":28,"finished":false,"league_entry_1":340643,"league_entry_1_points":0,"league_entry_2":333896,"league_entry_2_points":0,"started":false,"winning_league_entry":null,"winning_method":null},{"event":28,"finished":false,"league_entry_1":344571,"league_entry_1_points":0,"league_entry_2":422898,"league_entry_2_points":0,"started":false,"winning_league_entry":null,"winning_method":null},{"event":28,"finished":false,"league_entry_1":362777,"league_entry_1_points":0,"league_entry_2":400317,"league_entry_2_points":0,"started":false,"winning_league_entry":null,"winning_method":null},{"event":28,"finished":false,"league_entry_1":375720,"league_entry_1_points":0,"league_entry_2":392127,"league_entry_2_points":0,"started":false,"winning_league_entry":null,"winning_method":null},{"event":29,"finished":false,"league_entry_1":400317,"league_entry_1_points":0,"league_entry_2":333433,"league_entry_2_points":0,"started":false,"winning_league_entry":null,"winning_method":null},{"event":29,"finished":false,"league_entry_1":422898,"league_entry_1_points":0,"league_entry_2":392127,"league_entry_2_points":0,"started":false,"winning_league_entry":null,"winning_method":null},{"event":29,"finished":false,"league_entry_1":333896,"league_entry_1_points":0,"league_entry_2":375720,"league_entry_2_points":0,"started":false,"winning_league_entry":null,"winning_method":null},{"event":29,"finished":false,"league_entry_1":334690,"league_entry_1_points":0,"league_entry_2":362777,"league_entry_2_points":0,"started":false,"winning_league_entry":null,"winning_method":null},{"event":29,"finished":false,"league_entry_1":335338,"league_entry_1_points":0,"league_entry_2":344571,"league_entry_2_points":0,"started":false,"winning_league_entry":null,"winning_method":null},{"event":29,"finished":false,"league_entry_1":335523,"league_entry_1_points":0,"league_entry_2":340643,"league_entry_2_points":0,"started":false,"winning_league_entry":null,"winning_method":null},{"event":30,"finished":false,"league_entry_1":333433,"league_entry_1_points":0,"league_entry_2":335523,"league_entry_2_points":0,"started":false,"winning_league_entry":null,"winning_method":null},{"event":30,"finished":false,"league_entry_1":340643,"league_entry_1_points":0,"league_entry_2":335338,"league_entry_2_points":0,"started":false,"winning_league_entry":null,"winning_method":null},{"event":30,"finished":false,"league_entry_1":344571,"league_entry_1_points":0,"league_entry_2":334690,"league_entry_2_points":0,"started":false,"winning_league_entry":null,"winning_method":null},{"event":30,"finished":false,"league_entry_1":362777,"league_entry_1_points":0,"league_entry_2":333896,"league_entry_2_points":0,"started":false,"winning_league_entry":null,"winning_method":null},{"event":30,"finished":false,"league_entry_1":375720,"league_entry_1_points":0,"league_entry_2":422898,"league_entry_2_points":0,"started":false,"winning_league_entry":null,"winning_method":null},{"event":30,"finished":false,"league_entry_1":392127,"league_entry_1_points":0,"league_entry_2":400317,"league_entry_2_points":0,"started":false,"winning_league_entry":null,"winning_method":null},{"event":31,"finished":false,"league_entry_1":422898,"league_entry_1_points":0,"league_entry_2":333433,"league_entry_2_points":0,"started":false,"winning_league_entry":null,"winning_method":null},{"event":31,"finished":false,"league_entry_1":333896,"league_entry_1_points":0,"league_entry_2":400317,"league_entry_2_points":0,"started":false,"winning_league_entry":null,"winning_method":null},{"event":31,"finished":false,"league_entry_1":334690,"league_entry_1_points":0,"league_entry_2":392127,"league_entry_2_points":0,"started":false,"winning_league_entry":null,"winning_method":null},{"event":31,"finished":false,"league_entry_1":335338,"league_entry_1_points":0,"league_entry_2":375720,"league_entry_2_points":0,"started":false,"winning_league_entry":null,"winning_method":null},{"event":31,"finished":false,"league_entry_1":335523,"league_entry_1_points":0,"league_entry_2":362777,"league_entry_2_points":0,"started":false,"winning_league_entry":null,"winning_method":null},{"event":31,"finished":false,"league_entry_1":340643,"league_entry_1_points":0,"league_entry_2":344571,"league_entry_2_points":0,"started":false,"winning_league_entry":null,"winning_method":null},{"event":32,"finished":false,"league_entry_1":333433,"league_entry_1_points":0,"league_entry_2":340643,"league_entry_2_points":0,"started":false,"winning_league_entry":null,"winning_method":null},{"event":32,"finished":false,"league_entry_1":344571,"league_entry_1_points":0,"league_entry_2":335523,"league_entry_2_points":0,"started":false,"winning_league_entry":null,"winning_method":null},{"event":32,"finished":false,"league_entry_1":362777,"league_entry_1_points":0,"league_entry_2":335338,"league_entry_2_points":0,"started":false,"winning_league_entry":null,"winning_method":null},{"event":32,"finished":false,"league_entry_1":375720,"league_entry_1_points":0,"league_entry_2":334690,"league_entry_2_points":0,"started":false,"winning_league_entry":null,"winning_method":null},{"event":32,"finished":false,"league_entry_1":392127,"league_entry_1_points":0,"league_entry_2":333896,"league_entry_2_points":0,"started":false,"winning_league_entry":null,"winning_method":null},{"event":32,"finished":false,"league_entry_1":400317,"league_entry_1_points":0,"league_entry_2":422898,"league_entry_2_points":0,"started":false,"winning_league_entry":null,"winning_method":null},{"event":33,"finished":false,"league_entry_1":344571,"league_entry_1_points":0,"league_entry_2":333433,"league_entry_2_points":0,"started":false,"winning_league_entry":null,"winning_method":null},{"event":33,"finished":false,"league_entry_1":362777,"league_entry_1_points":0,"league_entry_2":340643,"league_entry_2_points":0,"started":false,"winning_league_entry":null,"winning_method":null},{"event":33,"finished":false,"league_entry_1":375720,"league_entry_1_points":0,"league_entry_2":335523,"league_entry_2_points":0,"started":false,"winning_league_entry":null,"winning_method":null},{"event":33,"finished":false,"league_entry_1":392127,"league_entry_1_points":0,"league_entry_2":335338,"league_entry_2_points":0,"started":false,"winning_league_entry":null,"winning_method":null},{"event":33,"finished":false,"league_entry_1":400317,"league_entry_1_points":0,"league_entry_2":334690,"league_entry_2_points":0,"started":false,"winning_league_entry":null,"winning_method":null},{"event":33,"finished":false,"league_entry_1":422898,"league_entry_1_points":0,"league_entry_2":333896,"league_entry_2_points":0,"started":false,"winning_league_entry":null,"winning_method":null},{"event":34,"finished":false,"league_entry_1":362777,"league_entry_1_points":0,"league_entry_2":333433,"league_entry_2_points":0,"started":false,"winning_league_entry":null,"winning_method":null},{"event":34,"finished":false,"league_entry_1":375720,"league_entry_1_points":0,"league_entry_2":344571,"league_entry_2_points":0,"started":false,"winning_league_entry":null,"winning_method":null},{"event":34,"finished":false,"league_entry_1":392127,"league_entry_1_points":0,"league_entry_2":340643,"league_entry_2_points":0,"started":false,"winning_league_entry":null,"winning_method":null},{"event":34,"finished":false,"league_entry_1":400317,"league_entry_1_points":0,"league_entry_2":335523,"league_entry_2_points":0,"started":false,"winning_league_entry":null,"winning_method":null},{"event":34,"finished":false,"league_entry_1":422898,"league_entry_1_points":0,"league_entry_2":335338,"league_entry_2_points":0,"started":false,"winning_league_entry":null,"winning_method":null},{"event":34,"finished":false,"league_entry_1":333896,"league_entry_1_points":0,"league_entry_2":334690,"league_entry_2_points":0,"started":false,"winning_league_entry":null,"winning_method":null},{"event":35,"finished":false,"league_entry_1":333433,"league_entry_1_points":0,"league_entry_2":333896,"league_entry_2_points":0,"started":false,"winning_league_entry":null,"winning_method":null},{"event":35,"finished":false,"league_entry_1":334690,"league_entry_1_points":0,"league_entry_2":422898,"league_entry_2_points":0,"started":false,"winning_league_entry":null,"winning_method":null},{"event":35,"finished":false,"league_entry_1":335338,"league_entry_1_points":0,"league_entry_2":400317,"league_entry_2_points":0,"started":false,"winning_league_entry":null,"winning_method":null},{"event":35,"finished":false,"league_entry_1":335523,"league_entry_1_points":0,"league_entry_2":392127,"league_entry_2_points":0,"started":false,"winning_league_entry":null,"winning_method":null},{"event":35,"finished":false,"league_entry_1":340643,"league_entry_1_points":0,"league_entry_2":375720,"league_entry_2_points":0,"started":false,"winning_league_entry":null,"winning_method":null},{"event":35,"finished":false,"league_entry_1":344571,"league_entry_1_points":0,"league_entry_2":362777,"league_entry_2_points":0,"started":false,"winning_league_entry":null,"winning_method":null},{"event":36,"finished":false,"league_entry_1":375720,"league_entry_1_points":0,"league_entry_2":333433,"league_entry_2_points":0,"started":false,"winning_league_entry":null,"winning_method":null},{"event":36,"finished":false,"league_entry_1":392127,"league_entry_1_points":0,"league_entry_2":362777,"league_entry_2_points":0,"started":false,"winning_league_entry":null,"winning_method":null},{"event":36,"finished":false,"league_entry_1":400317,"league_entry_1_points":0,"league_entry_2":344571,"league_entry_2_points":0,"started":false,"winning_league_entry":null,"winning_method":null},{"event":36,"finished":false,"league_entry_1":422898,"league_entry_1_points":0,"league_entry_2":340643,"league_entry_2_points":0,"started":false,"winning_league_entry":null,"winning_method":null},{"event":36,"finished":false,"league_entry_1":333896,"league_entry_1_points":0,"league_entry_2":335523,"league_entry_2_points":0,"started":false,"winning_league_entry":null,"winning_method":null},{"event":36,"finished":false,"league_entry_1":334690,"league_entry_1_points":0,"league_entry_2":335338,"league_entry_2_points":0,"started":false,"winning_league_entry":null,"winning_method":null},{"event":37,"finished":false,"league_entry_1":333433,"league_entry_1_points":0,"league_entry_2":334690,"league_entry_2_points":0,"started":false,"winning_league_entry":null,"winning_method":null},{"event":37,"finished":false,"league_entry_1":335338,"league_entry_1_points":0,"league_entry_2":333896,"league_entry_2_points":0,"started":false,"winning_league_entry":null,"winning_method":null},{"event":37,"finished":false,"league_entry_1":335523,"league_entry_1_points":0,"league_entry_2":422898,"league_entry_2_points":0,"started":false,"winning_league_entry":null,"winning_method":null},{"event":37,"finished":false,"league_entry_1":340643,"league_entry_1_points":0,"league_entry_2":400317,"league_entry_2_points":0,"started":false,"winning_league_entry":null,"winning_method":null},{"event":37,"finished":false,"league_entry_1":344571,"league_entry_1_points":0,"league_entry_2":392127,"league_entry_2_points":0,"started":false,"winning_league_entry":null,"winning_method":null},{"event":37,"finished":false,"league_entry_1":362777,"league_entry_1_points":0,"league_entry_2":375720,"league_entry_2_points":0,"started":false,"winning_league_entry":null,"winning_method":null},{"event":38,"finished":false,"league_entry_1":392127,"league_entry_1_points":0,"league_entry_2":333433,"league_entry_2_points":0,"started":false,"winning_league_entry":null,"winning_method":null},{"event":38,"finished":false,"league_entry_1":400317,"league_entry_1_points":0,"league_entry_2":375720,"league_entry_2_points":0,"started":false,"winning_league_entry":null,"winning_method":null},{"event":38,"finished":false,"league_entry_1":422898,"league_entry_1_points":0,"league_entry_2":362777,"league_entry_2_points":0,"started":false,"winning_league_entry":null,"winning_method":null},{"event":38,"finished":false,"league_entry_1":333896,"league_entry_1_points":0,"league_entry_2":344571,"league_entry_2_points":0,"started":false,"winning_league_entry":null,"winning_method":null},{"event":38,"finished":false,"league_entry_1":334690,"league_entry_1_points":0,"league_entry_2":340643,"league_entry_2_points":0,"started":false,"winning_league_entry":null,"winning_method":null},{"event":38,"finished":false,"league_entry_1":335338,"league_entry_1_points":0,"league_entry_2":335523,"league_entry_2_points":0,"started":false,"winning_league_entry":null,"winning_method":null}],"standings":[{"last_rank":1,"league_entry":400317,"matches_drawn":0,"matches_lost":7,"matches_played":38,"matches_won":19,"points_against":997,"points_for":1232,"rank":1,"rank_sort":1,"total":57},{"last_rank":2,"league_entry":392127,"matches_drawn":0,"matches_lost":10,"matches_played":38,"matches_won":16,"points_against":1026,"points_for":1180,"rank":2,"rank_sort":2,"total":48},{"last_rank":3,"league_entry":335523,"matches_drawn":2,"matches_lost":10,"matches_played":38,"matches_won":14,"points_against":1055,"points_for":1025,"rank":3,"rank_sort":3,"total":44},{"last_rank":4,"league_entry":362777,"matches_drawn":0,"matches_lost":12,"matches_played":38,"matches_won":14,"points_against":1007,"points_for":1122,"rank":4,"rank_sort":4,"total":42},{"last_rank":5,"league_entry":334690,"matches_drawn":0,"matches_lost":13,"matches_played":38,"matches_won":13,"points_against":1058,"points_for":1016,"rank":5,"rank_sort":5,"total":39},{"last_rank":6,"league_entry":340643,"matches_drawn":0,"matches_lost":13,"matches_played":38,"matches_won":13,"points_against":1024,"points_for":963,"rank":6,"rank_sort":6,"total":39},{"last_rank":7,"league_entry":333433,"matches_drawn":0,"matches_lost":13,"matches_played":38,"matches_won":13,"points_against":983,"points_for":937,"rank":7,"rank_sort":7,"total":39},{"last_rank":8,"league_entry":422898,"matches_drawn":1,"matches_lost":14,"matches_played":38,"matches_won":11,"points_against":1105,"points_for":1044,"rank":8,"rank_sort":8,"total":34},{"last_rank":9,"league_entry":335338,"matches_drawn":1,"matches_lost":14,"matches_played":38,"matches_won":11,"points_against":932,"points_for":1007,"rank":9,"rank_sort":9,"total":34},{"last_rank":10,"league_entry":333896,"matches_drawn":1,"matches_lost":15,"matches_played":38,"matches_won":10,"points_against":1066,"points_for":979,"rank":10,"rank_sort":10,"total":31},{"last_rank":11,"league_entry":344571,"matches_drawn":1,"matches_lost":15,"matches_played":38,"matches_won":10,"points_against":1018,"points_for":932,"rank":11,"rank_sort":11,"total":31},{"last_rank":12,"league_entry":375720,"matches_drawn":0,"matches_lost":17,"matches_played":38,"matches_won":9,"points_against":1125,"points_for":959,"rank":12,"rank_sort":12,"total":27}]}